MLorc_optim/__init__.py
MLorc_optim/optim/MLorc_AdamW.py
MLorc_optim/optim/MLorc_Adopt.py
MLorc_optim/optim/MLorc_CAME.py
MLorc_optim/optim/MLorc_DAdapt_Lion.py
MLorc_optim/optim/MLorc_Lion.py
MLorc_optim/optim/MLorc_Prodigy.py
MLorc_optim/optim/__init__.py
MLorc_optim/util/BF16_Stochastic_Rounding.py
MLorc_optim/util/Effective_Shape.py
MLorc_optim/util/OrthoGrad.py
MLorc_optim/util/Randomized_SVD.py
MLorc_optim/util/__init__.py
mlorc_optim-0.1.8.dist-info/licenses/LICENSE
mlorc_optim-0.1.8.dist-info/METADATA
mlorc_optim-0.1.8.dist-info/WHEEL
mlorc_optim-0.1.8.dist-info/top_level.txt
mlorc_optim-0.1.8.dist-info/RECORD
