Metadata-Version: 2.4
Name: MLorc_optim
Version: 0.1.8
Summary: Unofficial implementation of Momentum Low-Rank Compression (MLorc) for memory-efficient LLM fine-tuning
Home-page: https://github.com/Koratahiu/MLorc
Author: Koratahiu
Author-email: hiuhonor@gmail.com
License: Apache 2.0
Keywords: llm,fine-tuning,memory-efficient,low-rank,compression,pytorch,optimizer,adam,lion
Classifier: Programming Language :: Python :: 3
Classifier: License :: OSI Approved :: Apache Software License
Classifier: Operating System :: OS Independent
Classifier: Topic :: Scientific/Engineering :: Artificial Intelligence
Classifier: Topic :: Software Development :: Libraries :: Python Modules
Requires-Python: >=3.8
License-File: LICENSE
Requires-Dist: torch>=2.0
Dynamic: author
Dynamic: author-email
Dynamic: classifier
Dynamic: description
Dynamic: description-content-type
Dynamic: home-page
Dynamic: keywords
Dynamic: license
Dynamic: license-file
Dynamic: requires-dist
Dynamic: requires-python
Dynamic: summary
